{
  "connected": true,
  "broker": "Sandbox",
  "apiKey": "key",
  "balance": 500100,
  "marginAvailable": 500100,
  "positions": [],
  "orders": [
    {
      "orderId": "ORD-508793",
      "symbol": "ITC.NS",
      "side": "BUY",
      "quantity": 10,
      "price": 400,
      "orderType": "LIMIT",
      "status": "COMPLETED",
      "timestamp": "2026-07-11T16:02:55.448Z"
    },
    {
      "orderId": "ORD-227578",
      "symbol": "ITC.NS",
      "side": "SELL",
      "quantity": 10,
      "price": 410,
      "orderType": "LIMIT",
      "status": "COMPLETED",
      "timestamp": "2026-07-11T16:02:55.450Z"
    }
  ]
}